{
  "name": "ci-server",
  "default_attributes": {
  },
  "json_class": "Chef::Role",
  "run_list": [
    "recipe[apt::default]",
    "recipe[git::default]",
    "recipe[ruby::default]",
    "recipe[mysql::client]",
    "recipe[mysql::server]",
    "recipe[openssl::default]",
    "recipe[jenkins::default]",
    "recipe[php::default]",
    "recipe[php::php5]",
    "recipe[php::module_apc]",
    "recipe[php::module_curl]",
    "recipe[php::pear]",
    "recipe[php::module_memcached]",
    "recipe[phpunit::default]",
    "recipe[drush::head]",
    "recipe[php::module_mysql]",
    "recipe[postfix::default]"
  ],
  "description": "",
  "chef_type": "role",
  "override_attributes": {
  }
}
